aepsych_client/__init__.py
aepsych_client/client.py
aepsych_client/version.py
tests/__init__.py
tests/test_client.py
aepsych_client-0.5.0.dist-info/METADATA
aepsych_client-0.5.0.dist-info/WHEEL
aepsych_client-0.5.0.dist-info/top_level.txt
aepsych_client-0.5.0.dist-info/RECORD
