Metadata-Version: 2.4
Name: aepsych_client
Version: 0.5.0
Dynamic: description
Dynamic: description-content-type
